PyGrassClient/__init__.py
PyGrassClient/__version__.py
PyGrassClient/_async_core.py
PyGrassClient/_core.py
PyGrassClient/utils.py
PyGrassClient-2.0.6.dist-info/LICENSE
PyGrassClient-2.0.6.dist-info/METADATA
PyGrassClient-2.0.6.dist-info/WHEEL
PyGrassClient-2.0.6.dist-info/top_level.txt
PyGrassClient-2.0.6.dist-info/RECORD
