Metadata-Version: 2.1
Name: PyGrassClient
Version: 2.0.6
Summary: Get Grass Python Package
Home-page: https://github.com/Confusion-ymc/PyGrassClient
Author: confusion
Author-email: 1107238486@qq.com
License: Apache-2.0
Project-URL: Documentation, https://github.com/Confusion-ymc/PyGrassClient
Project-URL: Source, https://github.com/Confusion-ymc/PyGrassClient
Platform: all
Classifier: Development Status :: 5 - Production/Stable
Classifier: Environment :: Web Environment
Classifier: License :: OSI Approved :: Apache Software License
Classifier: Natural Language :: English
Classifier: Operating System :: OS Independent
Classifier: Programming Language :: Python
Classifier: Programming Language :: Python :: 3
Classifier: Programming Language :: Python :: 3.8
Classifier: Programming Language :: Python :: 3.9
Classifier: Programming Language :: Python :: 3.10
Classifier: Programming Language :: Python :: 3.11
Classifier: Programming Language :: Python :: 3.12
Classifier: Programming Language :: Python :: 3 :: Only
Classifier: Topic :: Software Development :: Libraries
License-File: LICENSE
Requires-Dist: loguru ==0.7.2
Requires-Dist: python-socks ==2.4.4
Requires-Dist: setuptools ==65.5.1
Requires-Dist: Faker ==23.2.1
Requires-Dist: requests[socks] ==2.31.0
Requires-Dist: websockets ==12.0
